bpt/__init__.py
bpt/__main__.py
bpt/main.py
bpt_py-0.0.5.dist-info/WHEEL
bpt_py-0.0.5.dist-info/entry_points.txt
bpt_py-0.0.5.dist-info/METADATA
bpt_py-0.0.5.dist-info/RECORD
