Metadata-Version: 2.3
Name: bpt-py
Version: 0.0.5
Summary: A zero-configuration C & C++ build and package tool (Python implementation)
Author: vector-of-bool
Author-email: vector-of-bool <vectorofbool@gmail.com>
Requires-Python: >=3.13
